minification_station/__init__.py
minification_station/config/__init__.py
minification_station/config/args.py
minification_station/config/constants.py
minification_station/config/enviornment_setup.py
minification_station/logging/__init__.py
minification_station/logging/decorators.py
minification_station/logging/setup_logging.py
minification_station/main.py
minification_station/processing/__init__.py
minification_station/processing/file_processor.py
minification_station/traversal/__init__.py
minification_station/traversal/directory_traversal.py
minification_station-0.1.4.dist-info/METADATA
minification_station-0.1.4.dist-info/WHEEL
minification_station-0.1.4.dist-info/entry_points.txt
minification_station-0.1.4.dist-info/RECORD
