Metadata-Version: 2.1
Name: minification-station
Version: 0.1.4
Summary: Designed to process and combine multiple files within a specified directory into a single output file.
Home-page: https://github.com/myinusa/minification-station
License: MIT
Keywords: automation,file processing,minification,text processing
Author: myinusa
Requires-Python: >=3.10,<4.0
Classifier: Environment :: Console
Classifier: Intended Audience :: Developers
Classifier: License :: OSI Approved :: MIT License
Classifier: Programming Language :: Python
Classifier: Programming Language :: Python :: 3
Classifier: Programming Language :: Python :: 3.10
Classifier: Programming Language :: Python :: 3.11
Classifier: Programming Language :: Python :: 3.12
Classifier: Programming Language :: Python :: 3 :: Only
Classifier: Programming Language :: Python :: 3.13
Requires-Dist: tqdm (>=4.66.5,<5.0.0)
Project-URL: Changelog, https://github.com/myinusa/minification-station/blob/main/CHANGELOG.md
Project-URL: Documentation, https://github.com/myinusa/minification-station/blob/main/README.md
Project-URL: Repository, https://github.com/myinusa/minification-station
